{"otherData": {},"traceEvents":[{},{"cat":"function","dur":121345,"name":"glfwInit","ph":"X","pid":0,"tid":908,"ts":208439879200.600},{"cat":"function","dur":394171,"name":"glfwCreateWindow","ph":"X","pid":0,"tid":908,"ts":208440000786.600},{"cat":"function","dur":1439,"name":"void OloEngine::OpenGLContext::Init(void)","ph":"X","pid":0,"tid":908,"ts":208440395097.500},{"cat":"function","dur":9,"name":"void OloEngine::WindowsWindow::SetVSync(bool)","ph":"X","pid":0,"tid":908,"ts":208440396608.800},{"cat":"function","dur":518470,"name":"void OloEngine::WindowsWindow::Init(const struct OloEngine::WindowProps &)","ph":"X","pid":0,"tid":908,"ts":208439878193.700},{"cat":"function","dur":518501,"name":"OloEngine::WindowsWindow::WindowsWindow(const struct OloEngine::WindowProps &)","ph":"X","pid":0,"tid":908,"ts":208439878192.300},{"cat":"function","dur":18,"name":"void OloEngine::OpenGLRendererAPI::Init(void)","ph":"X","pid":0,"tid":908,"ts":208440396736.000},{"cat":"function","dur":26,"name":"OloEngine::OpenGLVertexArray::OpenGLVertexArray(void)","ph":"X","pid":0,"tid":908,"ts":208440396791.700},{"cat":"function","dur":313,"name":"OloEngine::OpenGLVertexBuffer::OpenGLVertexBuffer(unsigned int)","ph":"X","pid":0,"tid":908,"ts":208440396868.300},{"cat":"function","dur":1,"name":"void OloEngine::OpenGLVertexBuffer::Bind(void) const","ph":"X","pid":0,"tid":908,"ts":208440397268.500},{"cat":"function","dur":50,"name":"void OloEngine::OpenGLVertexArray::AddVertexBuffer(const class std::shared_ptr<class OloEngine::VertexBuffer> &)","ph":"X","pid":0,"tid":908,"ts":208440397257.000},{"cat":"function","dur":2398,"name":"OloEngine::OpenGLIndexBuffer::OpenGLIndexBuffer(unsigned int *,unsigned int)","ph":"X","pid":0,"tid":908,"ts":208440398131.200},{"cat":"function","dur":1,"name":"void OloEngine::OpenGLIndexBuffer::Bind(void) const","ph":"X","pid":0,"tid":908,"ts":208440400633.300},{"cat":"function","dur":33,"name":"void OloEngine::OpenGLVertexArray::SetIndexBuffer(const class std::shared_ptr<class OloEngine::IndexBuffer> &)","ph":"X","pid":0,"tid":908,"ts":208440400631.200},{"cat":"function","dur":157,"name":"OloEngine::OpenGLTexture2D::OpenGLTexture2D(unsigned int,unsigned int)","ph":"X","pid":0,"tid":908,"ts":208440400715.700},{"cat":"function","dur":2828,"name":"void OloEngine::OpenGLTexture2D::SetData(void *,unsigned int)","ph":"X","pid":0,"tid":908,"ts":208440400923.700},{"cat":"function","dur":162,"name":"class std::basic_string<char,struct std::char_traits<char>,class std::allocator<char> > OloEngine::OpenGLShader::ReadFile(const class std::basic_string<char,struct std::char_traits<char>,class std::allocator<char> > &)","ph":"X","pid":0,"tid":908,"ts":208440403820.500},{"cat":"function","dur":40,"name":"class std::unordered_map<unsigned int,class std::basic_string<char,struct std::char_traits<char>,class std::allocator<char> >,struct std::hash<unsigned int>,struct std::equal_to<unsigned int>,class std::allocator<struct std::pair<unsigned int const ,class std::basic_string<char,struct std::char_traits<char>,class std::allocator<char> > > > > OloEngine::OpenGLShader::PreProcess(const class std::basic_string<char,struct std::char_traits<char>,class std::allocator<char> > &)","ph":"X","pid":0,"tid":908,"ts":208440404030.000},{"cat":"function","dur":897,"name":"void OloEngine::OpenGLShader::Compile(const class std::unordered_map<unsigned int,class std::basic_string<char,struct std::char_traits<char>,class std::allocator<char> >,struct std::hash<unsigned int>,struct std::equal_to<unsigned int>,class std::allocator<struct std::pair<unsigned int const ,class std::basic_string<char,struct std::char_traits<char>,class std::allocator<char> > > > > &)","ph":"X","pid":0,"tid":908,"ts":208440404106.700},{"cat":"function","dur":1345,"name":"OloEngine::OpenGLShader::OpenGLShader(const class std::basic_string<char,struct std::char_traits<char>,class std::allocator<char> > &)","ph":"X","pid":0,"tid":908,"ts":208440403816.600},{"cat":"function","dur":8,"name":"void OloEngine::OpenGLShader::Bind(void) const","ph":"X","pid":0,"tid":908,"ts":208440405204.800},{"cat":"function","dur":8517,"name":"void OloEngine::Renderer2D::Init(void)","ph":"X","pid":0,"tid":908,"ts":208440396783.300},{"cat":"function","dur":8601,"name":"void OloEngine::Renderer::Init(void)","ph":"X","pid":0,"tid":908,"ts":208440396734.000},{"cat":"function","dur":732,"name":"void OloEngine::ImGuiLayer::OnAttach(void)","ph":"X","pid":0,"tid":908,"ts":208440405375.000},{"cat":"function","dur":799,"name":"void OloEngine::Application::PushOverlay(class OloEngine::Layer *)","ph":"X","pid":0,"tid":908,"ts":208440405369.900},{"cat":"function","dur":528016,"name":"OloEngine::Application::Application(const class std::basic_string<char,struct std::char_traits<char>,class std::allocator<char> > &)","ph":"X","pid":0,"tid":908,"ts":208439878184.900},{"cat":"function","dur":8,"name":"OloEngine::OrthographicCamera::OrthographicCamera(float,float,float,float)","ph":"X","pid":0,"tid":908,"ts":208440406243.400},{"cat":"function","dur":133,"name":"stbi_load - OpenGLTexture2D::OpenGLTexture2D(const std::string&)","ph":"X","pid":0,"tid":908,"ts":208440406297.600},{"cat":"function","dur":610,"name":"OloEngine::OpenGLTexture2D::OpenGLTexture2D(const class std::basic_string<char,struct std::char_traits<char>,class std::allocator<char> > &)","ph":"X","pid":0,"tid":908,"ts":208440406296.000},{"cat":"function","dur":2150,"name":"void OloEngine::EditorLayer::OnAttach(void)","ph":"X","pid":0,"tid":908,"ts":208440406292.600},{"cat":"function","dur":2235,"name":"void OloEngine::Application::PushLayer(class OloEngine::Layer *)","ph":"X","pid":0,"tid":908,"ts":208440406283.900}]}