{"otherData": {},"traceEvents":[{},{"cat":"function","dur":32518,"name":"glfwInit","ph":"X","pid":0,"tid":14060,"ts":1589930131514.900},{"cat":"function","dur":237503,"name":"glfwCreateWindow","ph":"X","pid":0,"tid":14060,"ts":1589930164289.500},{"cat":"function","dur":2046,"name":"void OloEngine::OpenGLContext::Init(void)","ph":"X","pid":0,"tid":14060,"ts":1589930401979.900},{"cat":"function","dur":15,"name":"void OloEngine::WindowsWindow::SetVSync(bool)","ph":"X","pid":0,"tid":14060,"ts":1589930404136.100},{"cat":"function","dur":274342,"name":"void OloEngine::WindowsWindow::Init(const struct OloEngine::WindowProps &)","ph":"X","pid":0,"tid":14060,"ts":1589930129848.700},{"cat":"function","dur":274374,"name":"OloEngine::WindowsWindow::WindowsWindow(const struct OloEngine::WindowProps &)","ph":"X","pid":0,"tid":14060,"ts":1589930129847.100},{"cat":"function","dur":20,"name":"void OloEngine::OpenGLRendererAPI::Init(void)","ph":"X","pid":0,"tid":14060,"ts":1589930404264.400},{"cat":"function","dur":39,"name":"OloEngine::OpenGLVertexArray::OpenGLVertexArray(void)","ph":"X","pid":0,"tid":14060,"ts":1589930404325.100},{"cat":"function","dur":450,"name":"OloEngine::OpenGLVertexBuffer::OpenGLVertexBuffer(unsigned int)","ph":"X","pid":0,"tid":14060,"ts":1589930404429.500},{"cat":"function","dur":3,"name":"void OloEngine::OpenGLVertexBuffer::Bind(void) const","ph":"X","pid":0,"tid":14060,"ts":1589930405077.800},{"cat":"function","dur":91,"name":"void OloEngine::OpenGLVertexArray::AddVertexBuffer(const class std::shared_ptr<class OloEngine::VertexBuffer> &)","ph":"X","pid":0,"tid":14060,"ts":1589930405050.800},{"cat":"function","dur":2994,"name":"OloEngine::OpenGLIndexBuffer::OpenGLIndexBuffer(unsigned int *,unsigned int)","ph":"X","pid":0,"tid":14060,"ts":1589930406244.800},{"cat":"function","dur":2,"name":"void OloEngine::OpenGLIndexBuffer::Bind(void) const","ph":"X","pid":0,"tid":14060,"ts":1589930409385.800},{"cat":"function","dur":50,"name":"void OloEngine::OpenGLVertexArray::SetIndexBuffer(const class std::shared_ptr<class OloEngine::IndexBuffer> &)","ph":"X","pid":0,"tid":14060,"ts":1589930409381.900},{"cat":"function","dur":5790,"name":"OloEngine::OpenGLTexture2D::OpenGLTexture2D(unsigned int,unsigned int)","ph":"X","pid":0,"tid":14060,"ts":1589930409512.600},{"cat":"function","dur":481,"name":"void OloEngine::OpenGLTexture2D::SetData(void *,unsigned int)","ph":"X","pid":0,"tid":14060,"ts":1589930415481.900},{"cat":"function","dur":172,"name":"class std::basic_string<char,struct std::char_traits<char>,class std::allocator<char> > OloEngine::OpenGLShader::ReadFile(const class std::basic_string<char,struct std::char_traits<char>,class std::allocator<char> > &)","ph":"X","pid":0,"tid":14060,"ts":1589930416210.700},{"cat":"function","dur":55,"name":"class std::unordered_map<unsigned int,class std::basic_string<char,struct std::char_traits<char>,class std::allocator<char> >,struct std::hash<unsigned int>,struct std::equal_to<unsigned int>,class std::allocator<struct std::pair<unsigned int const ,class std::basic_string<char,struct std::char_traits<char>,class std::allocator<char> > > > > OloEngine::OpenGLShader::PreProcess(const class std::basic_string<char,struct std::char_traits<char>,class std::allocator<char> > &)","ph":"X","pid":0,"tid":14060,"ts":1589930416448.400},{"cat":"function","dur":12623,"name":"OloEngine::OpenGLShader::OpenGLShader(const class std::basic_string<char,struct std::char_traits<char>,class std::allocator<char> > &)","ph":"X","pid":0,"tid":14060,"ts":1589930416108.100},{"cat":"function","dur":24545,"name":"void OloEngine::Renderer2D::Init(void)","ph":"X","pid":0,"tid":14060,"ts":1589930404317.000},{"cat":"function","dur":24644,"name":"void OloEngine::Renderer::Init(void)","ph":"X","pid":0,"tid":14060,"ts":1589930404262.200},{"cat":"function","dur":666,"name":"void OloEngine::ImGuiLayer::OnAttach(void)","ph":"X","pid":0,"tid":14060,"ts":1589930428961.400},{"cat":"function","dur":732,"name":"void OloEngine::Application::PushOverlay(class OloEngine::Layer *)","ph":"X","pid":0,"tid":14060,"ts":1589930428948.000},{"cat":"function","dur":299934,"name":"OloEngine::Application::Application(const class std::basic_string<char,struct std::char_traits<char>,class std::allocator<char> > &,struct OloEngine::ApplicationCommandLineArgs)","ph":"X","pid":0,"tid":14060,"ts":1589930129839.300},{"cat":"function","dur":3,"name":"OloEngine::OrthographicCamera::OrthographicCamera(float,float,float,float)","ph":"X","pid":0,"tid":14060,"ts":1589930429823.000},{"cat":"function","dur":5321,"name":"stbi_load - OpenGLTexture2D::OpenGLTexture2D(const std::string&)","ph":"X","pid":0,"tid":14060,"ts":1589930429874.200},{"cat":"function","dur":6260,"name":"OloEngine::OpenGLTexture2D::OpenGLTexture2D(const class std::basic_string<char,struct std::char_traits<char>,class std::allocator<char> > &)","ph":"X","pid":0,"tid":14060,"ts":1589930429866.500},{"cat":"function","dur":8274,"name":"stbi_load - OpenGLTexture2D::OpenGLTexture2D(const std::string&)","ph":"X","pid":0,"tid":14060,"ts":1589930436201.200},{"cat":"function","dur":9120,"name":"OloEngine::OpenGLTexture2D::OpenGLTexture2D(const class std::basic_string<char,struct std::char_traits<char>,class std::allocator<char> > &)","ph":"X","pid":0,"tid":14060,"ts":1589930436200.900},{"cat":"function","dur":194,"name":"stbi_load - OpenGLTexture2D::OpenGLTexture2D(const std::string&)","ph":"X","pid":0,"tid":14060,"ts":1589930445419.800},{"cat":"function","dur":570,"name":"OloEngine::OpenGLTexture2D::OpenGLTexture2D(const class std::basic_string<char,struct std::char_traits<char>,class std::allocator<char> > &)","ph":"X","pid":0,"tid":14060,"ts":1589930445419.400},{"cat":"function","dur":127,"name":"stbi_load - OpenGLTexture2D::OpenGLTexture2D(const std::string&)","ph":"X","pid":0,"tid":14060,"ts":1589930446057.300},{"cat":"function","dur":296,"name":"OloEngine::OpenGLTexture2D::OpenGLTexture2D(const class std::basic_string<char,struct std::char_traits<char>,class std::allocator<char> > &)","ph":"X","pid":0,"tid":14060,"ts":1589930446057.100},{"cat":"function","dur":95,"name":"stbi_load - OpenGLTexture2D::OpenGLTexture2D(const std::string&)","ph":"X","pid":0,"tid":14060,"ts":1589930446406.800},{"cat":"function","dur":256,"name":"OloEngine::OpenGLTexture2D::OpenGLTexture2D(const class std::basic_string<char,struct std::char_traits<char>,class std::allocator<char> > &)","ph":"X","pid":0,"tid":14060,"ts":1589930446406.700},{"cat":"function","dur":2097,"name":"void OloEngine::EditorLayer::OnAttach(void)","ph":"X","pid":0,"tid":14060,"ts":1589930445414.700},{"cat":"function","dur":2216,"name":"void OloEngine::Application::PushLayer(class OloEngine::Layer *)","ph":"X","pid":0,"tid":14060,"ts":1589930445398.700}]}