{"otherData": {},"traceEvents":[{},{"cat":"function","dur":460,"name":"void OloEngine::Renderer2D::Shutdown(void)","ph":"X","pid":0,"tid":7392,"ts":1591533933962.700},{"cat":"function","dur":554,"name":"OloEngine::Application::~Application(void)","ph":"X","pid":0,"tid":7392,"ts":1591533933962.100},{"cat":"function","dur":0,"name":"void OloEngine::EditorLayer::OnDetach(void)","ph":"X","pid":0,"tid":7392,"ts":1591533934567.000},{"cat":"function","dur":75,"name":"OloEngine::OpenGLTexture2D::~OpenGLTexture2D(void)","ph":"X","pid":0,"tid":7392,"ts":1591533934612.200},{"cat":"function","dur":11,"name":"OloEngine::OpenGLTexture2D::~OpenGLTexture2D(void)","ph":"X","pid":0,"tid":7392,"ts":1591533934732.900},{"cat":"function","dur":12,"name":"OloEngine::OpenGLTexture2D::~OpenGLTexture2D(void)","ph":"X","pid":0,"tid":7392,"ts":1591533934773.900},{"cat":"function","dur":10,"name":"OloEngine::OpenGLTexture2D::~OpenGLTexture2D(void)","ph":"X","pid":0,"tid":7392,"ts":1591533934816.700},{"cat":"function","dur":10,"name":"OloEngine::OpenGLTexture2D::~OpenGLTexture2D(void)","ph":"X","pid":0,"tid":7392,"ts":1591533934859.900},{"cat":"function","dur":1270,"name":"void OloEngine::ImGuiLayer::OnDetach(void)","ph":"X","pid":0,"tid":7392,"ts":1591533934982.200},{"cat":"function","dur":29910,"name":"void OloEngine::WindowsWindow::Shutdown(void)","ph":"X","pid":0,"tid":7392,"ts":1591533936315.300},{"cat":"function","dur":30053,"name":"OloEngine::WindowsWindow::~WindowsWindow(void)","ph":"X","pid":0,"tid":7392,"ts":1591533936315.000}]}